rich_packager.py
RichPackager-0.1.1.dist-info/DESCRIPTION.rst
RichPackager-0.1.1.dist-info/METADATA
RichPackager-0.1.1.dist-info/RECORD
RichPackager-0.1.1.dist-info/WHEEL
RichPackager-0.1.1.dist-info/metadata.json
RichPackager-0.1.1.dist-info/top_level.txt
RichPackager-0.1.1.dist-info/zip-safe
