Metadata-Version: 2.0
Name: RichPackager
Version: 0.1.1
Summary: Python package suite to ship with standard package (built by Setuptools), project data files, offline dependence and others.
Home-page: UNKNOWN
Author: Wang
Author-email: taptube@gmail.com
License: UNKNOWN
Platform: UNKNOWN
Classifier: Development Status :: 4 - Beta
Classifier: License :: OSI Approved :: MIT License
Classifier: Programming Language :: Python
Classifier: Programming Language :: Python :: 2
Classifier: Programming Language :: Python :: 2.7
Classifier: Programming Language :: Python :: 3
Classifier: Programming Language :: Python :: 3.4
Classifier: Programming Language :: Python :: 3.5
Classifier: Intended Audience :: Developers
Classifier: Operating System :: OS Independent
